omotes_sdk/__init__.py
omotes_sdk/config.py
omotes_sdk/job.py
omotes_sdk/omotes_interface.py
omotes_sdk/py.typed
omotes_sdk/queue_names.py
omotes_sdk/types.py
omotes_sdk/workflow_type.py
omotes_sdk/internal/__init__.py
omotes_sdk/internal/common/__init__.py
omotes_sdk/internal/common/app_logging.py
omotes_sdk/internal/common/broker_interface.py
omotes_sdk/internal/common/config.py
omotes_sdk/internal/common/esdl_util.py
omotes_sdk/internal/orchestrator_worker_events/__init__.py
omotes_sdk/internal/orchestrator_worker_events/esdl_messages.py
omotes_sdk/internal/orchestrator_worker_events/task_type.py
omotes_sdk/internal/worker/__init__.py
omotes_sdk/internal/worker/configs.py
omotes_sdk/internal/worker/worker.py
omotes_sdk_python-4.3.2.dist-info/LICENSE
omotes_sdk_python-4.3.2.dist-info/METADATA
omotes_sdk_python-4.3.2.dist-info/WHEEL
omotes_sdk_python-4.3.2.dist-info/top_level.txt
omotes_sdk_python-4.3.2.dist-info/RECORD
