Metadata-Version: 2.1
Name: omotes-sdk-python
Version: 4.3.2
Summary: Python implementation of the OMOTES SDK through jobs which may be submitted, receive status updates for submitted jobs or delete submitted jobs.
Author-email: Sebastiaan la Fleur <sebastiaan.lafleur@tno.nl>, Mark Vrijlandt <mark.vrijlandt@tno.nl>
License:       Apache License
Project-URL: homepage, https://www.nwn.nu
Project-URL: documentation, https://readthedocs.org
Project-URL: repository, https://github.com/Nieuwe-Warmte-Nu/omotes-sdk-python
Project-URL: changelog, https://github.com/Nieuwe-Warmte-Nu/omotes-sdk-python/blob/main/CHANGELOG.md
Classifier: License :: OSI Approved :: Apache Software License
Classifier: Programming Language :: Python :: 3
Classifier: Programming Language :: Python :: 3.11
Classifier: Operating System :: OS Independent
Classifier: Development Status :: 4 - Beta
Classifier: Intended Audience :: Developers
Classifier: Intended Audience :: Science/Research
Classifier: Intended Audience :: Information Technology
Classifier: Topic :: Scientific/Engineering
Classifier: Topic :: Scientific/Engineering :: Mathematics
Classifier: Topic :: Scientific/Engineering :: Physics
Requires-Python: >=3.9
License-File: LICENSE
Requires-Dist: aio-pika<9.5,~=9.4
Requires-Dist: omotes-sdk-protocol~=1.2
Requires-Dist: pyesdl~=25.7
Requires-Dist: pamqp~=3.3
Requires-Dist: celery~=5.3
Requires-Dist: typing-extensions~=4.11
Requires-Dist: streamcapture~=1.2.5
Provides-Extra: dev
Requires-Dist: setuptools~=75.6.0; extra == "dev"
Requires-Dist: wheel~=0.45.1; extra == "dev"
Requires-Dist: setuptools-git-versioning<3,>=2.0; extra == "dev"
Requires-Dist: black~=24.10.0; extra == "dev"
Requires-Dist: flake8==7.1.1; extra == "dev"
Requires-Dist: flake8-pyproject~=1.2.3; extra == "dev"
Requires-Dist: flake8-docstrings~=1.7.0; extra == "dev"
Requires-Dist: flake8-quotes~=3.4.0; extra == "dev"
Requires-Dist: flake8-bugbear~=24.10.31; extra == "dev"
Requires-Dist: flake8-tuple~=0.4.1; extra == "dev"
Requires-Dist: pytest~=8.3.4; extra == "dev"
Requires-Dist: pytest-cov~=6.0.0; extra == "dev"
Requires-Dist: mypy~=1.13.0; extra == "dev"
Requires-Dist: isort==5.13.2; extra == "dev"
Requires-Dist: build~=1.2.2; extra == "dev"
Requires-Dist: mypy-protobuf~=3.5.0; extra == "dev"
